sort/__init__.py
sort/bubble_sort.py
sort/insertion_sort.py
sort/quick_sort.py
sort/selecting_sort.py
sort_pckg_frarg-0.1.dist-info/METADATA
sort_pckg_frarg-0.1.dist-info/WHEEL
sort_pckg_frarg-0.1.dist-info/top_level.txt
sort_pckg_frarg-0.1.dist-info/RECORD
