Metadata-Version: 2.1
Name: sort-pckg-frarg
Version: 0.1
Summary: sorting algorithms
Home-page: UNKNOWN
Author: UNKNOWN
Author-email: UNKNOWN
License: MIT
Keywords: algorithm sort wonderful
Platform: UNKNOWN
Classifier: Development Status :: 3 - Alpha
Classifier: License :: OSI Approved :: MIT License
Classifier: Programming Language :: Python :: 3.7
